abb_robotraconteur_driver_hmp/__init__.py
abb_robotraconteur_driver_hmp/__main__.py
abb_robotraconteur_driver_hmp/_joint_control_req.py
abb_robotraconteur_driver_hmp/_motion_program.py
abb_robotraconteur_driver_hmp/_motion_program_conv.py
abb_robotraconteur_driver_hmp/_rws.py
abb_robotraconteur_driver_hmp/abb_robotraconteur_driver_hmp.py
abb_robotraconteur_driver_hmp/experimental.abb_robot.motion_program.robdef
abb_robotraconteur_driver_hmp/experimental.abb_robot.robdef
abb_robotraconteur_driver_hmp/experimental.robotics.motion_program.robdef
abb_robotraconteur_driver_hmp-0.2.0.dist-info/LICENSE.txt
abb_robotraconteur_driver_hmp-0.2.0.dist-info/METADATA
abb_robotraconteur_driver_hmp-0.2.0.dist-info/WHEEL
abb_robotraconteur_driver_hmp-0.2.0.dist-info/top_level.txt
abb_robotraconteur_driver_hmp-0.2.0.dist-info/RECORD
