Metadata-Version: 2.1
Name: abb-robotraconteur-driver-hmp
Version: 0.2.0
Summary: ABB Robot Raconteur Driver HMP
Home-page: https://github.com/johnwason/abb_robotraconteur_driver_hmp
License-File: LICENSE.txt
Requires-Dist: RobotRaconteur
Requires-Dist: RobotRaconteurCompanion
Requires-Dist: robotraconteur-abstract-robot
Requires-Dist: numpy
Requires-Dist: abb-robot-client
Requires-Dist: abb-motion-program-exec
Requires-Dist: aioconsole
